{
  "config_name": "optimal_2025-10-02_20-30-21",
  "description": "Optimal configuration found from simulation run at 2025-10-02_20-30-21. Win rate: 58.8%, Total points: 2124.8, PPG: 125.0, Consistency: 10.9",
  "parameters": {
    "ADP_EXCELLENT_MULTIPLIER": [
      1.05
    ],
    "ADP_GOOD_MULTIPLIER": [
      1.29
    ],
    "ADP_POOR_MULTIPLIER": [
      0.41,
      0.42,
      0.43,
      0.44,
      0.47,
      0.48,
      0.51,
      0.52,
      0.53,
      0.54,
      0.55,
      0.57,
      0.58,
      0.59,
      0.6,
      0.61,
      0.62,
      0.63,
      0.64,
      0.65,
      0.66,
      0.67,
      0.68,
      0.69,
      0.7,
      0.71,
      0.72,
      0.73,
      0.75,
      0.76,
      0.77,
      0.78,
      0.79,
      0.8,
      0.81,
      0.82,
      0.83,
      0.86,
      0.87,
      0.88,
      0.89,
      0.9,
      0.91,
      0.92,
      0.93,
      0.94,
      0.95,
      0.97,
      0.98,
      0.99
    ],
    "BASE_BYE_PENALTY": [
      9.6
    ],
    "DRAFT_ORDER_PRIMARY_BONUS": [
      51.08
    ],
    "DRAFT_ORDER_SECONDARY_BONUS": [
      38.76
    ],
    "INJURY_PENALTIES_HIGH": [
      23.53
    ],
    "INJURY_PENALTIES_MEDIUM": [
      15.64
    ],
    "MATCHUP_EXCELLENT_MULTIPLIER": [
      1.15
    ],
    "MATCHUP_GOOD_MULTIPLIER": [
      1.1
    ],
    "MATCHUP_NEUTRAL_MULTIPLIER": [
      1.0
    ],
    "MATCHUP_POOR_MULTIPLIER": [
      0.9
    ],
    "MATCHUP_VERY_POOR_MULTIPLIER": [
      0.8
    ],
    "NORMALIZATION_MAX_SCALE": [
      90
    ],
    "PLAYER_RATING_EXCELLENT_MULTIPLIER": [
      1.2
    ],
    "PLAYER_RATING_GOOD_MULTIPLIER": [
      1.1
    ],
    "PLAYER_RATING_POOR_MULTIPLIER": [
      0.9
    ],
    "TEAM_EXCELLENT_MULTIPLIER": [
      1.12
    ],
    "TEAM_GOOD_MULTIPLIER": [
      1.06
    ],
    "TEAM_POOR_MULTIPLIER": [
      0.94
    ]
  }
}