{
    "name": "Hero RB",
    "description": "Draft one elite RB early, then WRs, fill remaining RBs in middle rounds.",
    "DRAFT_ORDER": [
      {
        "RB": "P",
        "WR": "S"
      },
      {
        "WR": "P",
        "RB": "S"
      },
      {
        "WR": "P",
        "RB": "S"
      },
      {
        "WR": "P",
        "RB": "S"
      },
      {
        "TE": "P",
        "WR": "S"
      },
      {
        "WR": "P",
        "RB": "S"
      },
      {
        "QB": "P",
        "FLEX": "S"
      },
      {
        "RB": "P",
        "WR": "S"
      },
      {
        "TE": "P",
        "FLEX": "S"
      },
      {
        "RB": "P",
        "WR": "S"
      },
      {
        "QB": "P",
        "FLEX": "S"
      },
      {
        "RB": "P",
        "WR": "S"
      },
      {
        "K": "P",
        "FLEX": "S"
      },
      {
        "DST": "P",
        "FLEX": "S"
      },
      {
        "FLEX": "P"
      }
    ]
}
