{
    "name": "RB Heavy Early",
    "description": "Load up on RBs in the first 4 rounds, then fill WRs and premium positions.",
    "DRAFT_ORDER": [
      {
        "RB": "P",
        "WR": "S"
      },
      {
        "RB": "P",
        "WR": "S"
      },
      {
        "RB": "P",
        "WR": "S"
      },
      {
        "RB": "P",
        "WR": "S"
      },
      {
        "WR": "P",
        "RB": "S"
      },
      {
        "WR": "P",
        "RB": "S"
      },
      {
        "TE": "P",
        "WR": "S"
      },
      {
        "WR": "P",
        "RB": "S"
      },
      {
        "QB": "P",
        "FLEX": "S"
      },
      {
        "TE": "P",
        "WR": "S"
      },
      {
        "WR": "P",
        "RB": "S"
      },
      {
        "QB": "P",
        "FLEX": "S"
      },
      {
        "K": "P",
        "FLEX": "S"
      },
      {
        "DST": "P",
        "FLEX": "S"
      },
      {
        "FLEX": "P"
      }
    ]
}
